emlangkit/__init__.py
emlangkit/language.py
emlangkit/metrics/__init__.py
emlangkit/metrics/bosdis.py
emlangkit/metrics/entropy.py
emlangkit/metrics/has.py
emlangkit/metrics/mpn.py
emlangkit/metrics/mutual_information.py
emlangkit/metrics/nc_npmi.py
emlangkit/metrics/posdis.py
emlangkit/metrics/topsim.py
emlangkit/metrics/zla.py
emlangkit/utils/__init__.py
emlangkit/utils/array_ops.py
emlangkit-0.3.0.dist-info/LICENSE
emlangkit-0.3.0.dist-info/METADATA
emlangkit-0.3.0.dist-info/WHEEL
emlangkit-0.3.0.dist-info/top_level.txt
emlangkit-0.3.0.dist-info/RECORD
