Metadata-Version: 2.2
Name: emlangkit
Version: 0.3.0
Summary:  Emergent Language Analysis Toolkit
Author-email: Olaf Lipinski <o.lipinski@soton.ac.uk>
License: MIT License
Project-URL: Homepage, https://github.com/olipinski/emlangkit
Project-URL: Bug Tracker, https://github.com/olipinski/emlangkit/issues
Keywords: emergent communication,emergent language
Classifier: Programming Language :: Python :: 3 :: Only
Classifier: Programming Language :: Python :: 3.9
Classifier: Programming Language :: Python :: 3.10
Classifier: Programming Language :: Python :: 3.11
Classifier: Programming Language :: Python :: 3.12
Classifier: License :: OSI Approved :: MIT License
Classifier: Operating System :: OS Independent
Classifier: Development Status :: 3 - Alpha
Classifier: Intended Audience :: Science/Research
Classifier: Topic :: Scientific/Engineering :: Artificial Intelligence
Requires-Python: >=3.9
License-File: LICENSE
Requires-Dist: numpy
Requires-Dist: scipy
Requires-Dist: editdistance
